
[
    {
      "id": 1,
      "fullName": "Jenny Chan",
      "email": "jenny.chan@email.com"
    },
    {
      "id": 2,
      "fullName": "Jessica warren",
      "email": "jessica.warren@email.com"
    },
    {
      "id": 3,
      "fullName": "Tony Frank",
      "email": "tony.frank@email.com"
    },
    {
      "id": 4,
      "fullName": "Jeremy Clark",
      "email": "jeremy.clark@email.com"
    },
    {
      "id": 5,
      "fullName": "Raymond Edwards",
      "email": "raymon.edwards@email.com"

    }
  ]